free_verify_proxy/__init__.py
free_verify_proxy/free_verify_proxy.py
free_verify_proxy/proxy.py
free_verify_proxy/proxy_verify.py
free_verify_proxy-2.0.4.dist-info/LICENSE.txt
free_verify_proxy-2.0.4.dist-info/METADATA
free_verify_proxy-2.0.4.dist-info/WHEEL
free_verify_proxy-2.0.4.dist-info/top_level.txt
free_verify_proxy-2.0.4.dist-info/RECORD
