Metadata-Version: 2.1
Name: free-verify-proxy
Version: 2.0.4
Summary: A simple package to provide http and https working proxy lists.
Home-page: https://github.com/mominurr/free_verify_proxy
Author: Mominur Rahman
Author-email: mominurr518@email.com
Classifier: Programming Language :: Python :: 3
Classifier: License :: OSI Approved :: MIT License
Classifier: Operating System :: OS Independent
License-File: LICENSE.txt
Requires-Dist: requests
Requires-Dist: beautifulsoup4
Requires-Dist: curl-cffi
Requires-Dist: country-converter
